Workbook

Sheet LISTADO
C1: CI COLOMBIAN MINT | K1: Codigo: GMC-FR08
C2: LISTADO DE VERIFICACION | K2: Versión:1
K3: Fecha de aprobación: 01/07/2021
A5: 1. PLANIFICACIÓN DE LA AUDITORIA
A6: FECHA | C6: 2026-07-09 | G6: PROCESO | H6: GHM GESTION HUMANA
A7: AUDITOR | C7: Luis Arango | G7: AUDITADO | H7: Milady López / Isabel Escobar
A8: DOCUMENTOS RELACIONADOS | C8: GMC-FR07 Plan Auditorías 2026 · Res. 015/2016 Art. 4º · GMC-FR08 | G8: REQUISITOS | H8: OEA 1.7, OEA 1.8, OEA 5.1, OEA 5.2, OEA 5.3, OEA 5.4, OEA 5.5, OEA 5.6, OEA 9.2, OEA 9.3, OEA 9.4
A9: OBJETIVO | C9: Validar el cumplimiento de los requisitos de la resolución 015 de 2016 para el OEA Exportador | G9: ALCANCE | H9: Todos los requisitos OEA de la resolución 015 de 2016 para operador económico autorizado tipo Exportador.
A10: 2. ENTREVISTA
A11: PREGUNTAS | G11: COMENTARIOS | K11: CUMPLE
K12: SI | L12: NO
A13: 1
A14: 2
A15: 3
A16: 4
A17: 5
A18: 6
A19: 7
A20: 8
A21: 9
A22: 10
A24: 3. HALLAZGOS INDIVIDUALES
A28: 4. ASPECTOS POR RESALTAR (AR)
A29: 1
A30: 2
A31: 3
A32: 4
A33: 5
A34: 5. ASPECTOS POR MEJORAR (AM)
A35: 1
A36: 2
A37: 3
A38: 4
A39: 5
A41: REQUISITO | C41: NO CONFORMIDAD (NC) | H41: RIESGO | K41: Nº AC
A42: 1
A43: 2
A44: 3
A45: 4
A46: 5
A48: TOTAL AR | B48: =COUNTA(B29) -> 0 | C48: TOTAL AM | D48: =COUNTA(B35:L39) -> 0 | E48: TOTAL NC | G48: =COUNTA(C42:G46) -> 0 | H48: NIVEL IMPLEMENTACIÓN | J48: NIVEL EFICACIA

Sheet Banco Preguntas
A1: Requisito | B1: Proceso | C1: Responsable | D1: Descripción del requisito | E1: Preguntas Sugeridas Auditoría Interna
A2: OEA 1.7 | B2: GHM GESTION HUMANA | C2: =+LISTADO!$H$7 -> Milady López / Isabel Escobar | D2: Identificar y mantener actualizados los cargos críticos relacionados con la seguridad de la cadena de suministro. | E2: ¿Mencione el sistema o matriz de riesgos implementado para identificar los cargos críticos. indique la ubicación en el documento (numeral, ítem, párrafos, página, etc.) Indique versión, fecha e identificación en el SGD. Para sustentar, presente evidencia documental vigente de Colombian Mint, tales como: GHM-MT01 (Matriz de Cargos Críticos), GHM-MT04 (Matriz de Estudio Socioeconómico y Visitas Domiciliarias)?
A3: OEA 1.7 | B3: GHM GESTION HUMANA | C3: =+LISTADO!$H$7 -> Milady López / Isabel Escobar | D3: Identificar y mantener actualizados los cargos críticos relacionados con la seguridad de la cadena de suministro. | E3: ¿Cuenta con un documento(s) que contenga la metodología para medir el nivel de riesgo de los cargos críticos en la CSI? indique la ubicación en el documento (numeral, ítem, párrafos, página, etc.) Indique versión, fecha e identificación en el SGD. Para sustentar, presente evidencia documental vigente de Colombian Mint, tales como: GHM-MT01 (Matriz de Cargos Críticos), GHM-GU02 (Guía de cargos críticos)?
A4: OEA 1.7 | B4: GHM GESTION HUMANA | C4: =+LISTADO!$H$7 -> Milady López / Isabel Escobar | D4: Identificar y mantener actualizados los cargos críticos relacionados con la seguridad de la cadena de suministro. | E4: ¿Señale la fecha en que se realizó la última actualización de la evaluación de criticidad de los cargos. ¿Qué registros o documentos (GHM-MT01 (Matriz de Cargos Críticos), GHM-GU02 (Guía de cargos críticos)) demuestran el cumplimiento de lo solicitado?
A5: OEA 1.7 | B5: GHM GESTION HUMANA | C5: =+LISTADO!$H$7 -> Milady López / Isabel Escobar | D5: Identificar y mantener actualizados los cargos críticos relacionados con la seguridad de la cadena de suministro. | E5: ¿Relacione las evidencias de implementación (Ej. Matriz de evaluación, procedimiento, instructivo, metodología, soportes de evaluación, actas de reunión, etc.). Para sustentar, presente evidencia documental vigente de Colombian Mint, tales como: GHM-MT04 (Matriz de Estudio Socioeconómico y Visitas Domiciliarias), GHM-MT01 (Matriz de Cargos Críticos)?
A6: OEA 1.7 | B6: GHM GESTION HUMANA | C6: =+LISTADO!$H$7 -> Milady López / Isabel Escobar | D6: Identificar y mantener actualizados los cargos críticos relacionados con la seguridad de la cadena de suministro. | E6: ¿según criterios de auditoría OEA (ISO 19011) para el requisito OEA 1.7: Organigrama de seguridad. ¿Qué evidencia objetiva presenta el auditado? Documentos de referencia: GPE-DC02 (Organigrama General), GHM-FR10 (Lista de Chequeo Selección y Contratación)?
A7: OEA 1.7 | B7: GHM GESTION HUMANA | C7: =+LISTADO!$H$7 -> Milady López / Isabel Escobar | D7: Identificar y mantener actualizados los cargos críticos relacionados con la seguridad de la cadena de suministro. | E7: ¿según criterios de auditoría OEA (ISO 19011) para el requisito OEA 1.7: Listado de cargos críticos con funciones. ¿Qué evidencia objetiva presenta el auditado? Documentos de referencia: GHM-MT01 (Matriz de Cargos Críticos), GHM-GU02 (Guía de cargos críticos)?
A8: OEA 1.7 | B8: GHM GESTION HUMANA | C8: =+LISTADO!$H$7 -> Milady López / Isabel Escobar | D8: Identificar y mantener actualizados los cargos críticos relacionados con la seguridad de la cadena de suministro. | E8: ¿Verifique el documento GHM-FR16 (Descripción del Cargo). ¿Está vigente, identificado en el SGD, aprobado por la autoridad competente y en aplicación para el requisito OEA 1.7?
A9: OEA 1.7 | B9: GHM GESTION HUMANA | C9: =+LISTADO!$H$7 -> Milady López / Isabel Escobar | D9: Identificar y mantener actualizados los cargos críticos relacionados con la seguridad de la cadena de suministro. | E9: ¿en la auditoría ARCA (marzo 2025) se registró respecto a OEA 1.7: "En la verificación de la GHM-MT01 matriz de cargos críticos de la compañía se evidencia que Asistente administrativo y experiencia (Aura de aguas Domínguez) tiene acceso a información del proceso de exportación, sin emba". ¿Cuál es el estado actual de las acciones correctivas y su verificación efectiva? Evidencia de cierre sugerida: GHM-MT01 (Matriz de Cargos Críticos)?
A10: OEA 1.7 | B10: GHM GESTION HUMANA | C10: =+LISTADO!$H$7 -> Milady López / Isabel Escobar | D10: Identificar y mantener actualizados los cargos críticos relacionados con la seguridad de la cadena de suministro. | E10: ¿El requisito OEA 1.7 exige: "Identificar y mantener actualizados los cargos críticos relacionados con la seguridad de la cadena de suministro." ¿Qué controles operativos y registros demuestran su cumplimiento sostenido en Colombian Mint?
A11: OEA 1.7 | B11: GHM GESTION HUMANA | C11: =+LISTADO!$H$7 -> Milady López / Isabel Escobar | D11: Identificar y mantener actualizados los cargos críticos relacionados con la seguridad de la cadena de suministro. | E11: ¿Presente el GHM-MT02 y sus registros asociados. ¿Con qué periodicidad se actualiza, quién es el responsable y cómo se evidencia su aplicación al requisito OEA 1.7?
A12: OEA 1.8 | B12: GHM GESTION HUMANA | C12: =+LISTADO!$H$7 -> Milady López / Isabel Escobar | D12: Tener establecidas cláusulas de confidencialidad y de responsabilidad en los contratos de su personal vinculado. | E12: ¿Mencione el documento o formato en el que se evidencia las cláusulas de confidencialidad y responsabilidad, si estas se encuentran en un contrato, mencione el número de la cláusula de confidencialidad y de responsabilidad. Para sustentar, presente evidencia documental vigente de Colombian Mint, tales como: GTI-GU01 (Política de Seguridad de la Información, si aplica a confidencialidad ), GHM-FR28 (Contrato Individual de Trabajo a Término Indefinido)?
A13: OEA 1.8 | B13: GHM GESTION HUMANA | C13: =+LISTADO!$H$7 -> Milady López / Isabel Escobar | D13: Tener establecidas cláusulas de confidencialidad y de responsabilidad en los contratos de su personal vinculado. | E13: ¿Cuenta con un documento(s) con los lineamientos para establecer la cláusula? indique la ubicación en el documento (numeral, ítem, párrafos, página, etc.). Indique versión, fecha e identificación en el SGD. Para sustentar, presente evidencia documental vigente de Colombian Mint, tales como: GTI-GU01 (Política de Seguridad de la Información, si aplica a confidencialidad ), GHM-FR28 (Contrato Individual de Trabajo a Término Indefinido)?
... A111: OEA 9.4 | B111: GHM GESTION HUMANA | C111: =+LISTADO!$H$7 -> Milady López / Isabel Escobar | D111: Debe tener implementado un programa de entrenamiento para manejo de situaciones de pánico que sea acorde con las necesidades de las áreas críticas. | E111: ¿Existen indicadores o métricas definidos para verificar la eficacia de los controles del requisito OEA 9.4? Presente resultados del último periodo evaluado?
